imagecrypto/_init_.py
imagecrypto/aes_ccm_128.py
imagecrypto/aes_eax_128.py
imagecrypto/aes_gcm_128.py
imagecrypto/aes_gcm_256.py
imagecrypto/chacha20_poly1305.py
imagecrypto/main.py
imagecrypto/salsa20.py
imagecrypto-0.6.0.dist-info/LICENSE
imagecrypto-0.6.0.dist-info/METADATA
imagecrypto-0.6.0.dist-info/WHEEL
imagecrypto-0.6.0.dist-info/RECORD
