Metadata-Version: 2.1
Name: imagecrypto
Version: 0.6.0
Summary: ImageCrypto is a Python package for secure image encryption using various symmetric ciphers with asymmetric Elliptic Curve Cryptography (ECC) for key generation.
Home-page: https://github.com/nidhi-bhatt/imagecrypto
License: MIT
Keywords: cryptography,image encryption,ECC,AES,ChaCha20,Salsa20
Author: Nidhi Bhatt
Author-email: itsnibhatt@gmail.com
Requires-Python: >=3.9,<4.0
Classifier: License :: OSI Approved :: MIT License
Classifier: Programming Language :: Python :: 3
Classifier: Programming Language :: Python :: 3.9
Classifier: Programming Language :: Python :: 3.10
Classifier: Programming Language :: Python :: 3.11
Classifier: Programming Language :: Python :: 3.12
Requires-Dist: cryptography (>=42.0.0,<43.0.0)
Requires-Dist: matplotlib (>=3.4.0,<4.0.0)
Requires-Dist: numpy (>=2.0.0,<3.0.0)
Requires-Dist: opencv-python (>=4.5.0,<5.0.0)
Requires-Dist: pycryptodome (>=3.10.0,<4.0.0)
Project-URL: Repository, https://github.com/nidhi-bhatt/imagecrypto
